[
  {
    "alt": "Tesla logo",
    "url": "https://www.carlogos.org/car-logos/tesla-logo.png"
  },
  {
    "alt": "Toyota logo",
    "url": "https://www.carlogos.org/car-logos/toyota-logo.png"
  },
  {
    "alt": "Ford logo",
    "url": "https://www.carlogos.org/car-logos/ford-logo.png"
  },
  {
    "alt": "Honda logo",
    "url": "https://www.carlogos.org/car-logos/honda-logo.png"
  },
  {
    "alt": "BMW logo",
    "url": "https://www.carlogos.org/car-logos/bmw-logo.png"
  },
  {
    "alt": "Subaru logo",
    "url": "https://www.carlogos.org/car-logos/subaru-logo.png"
  },
  {
    "alt": "Hyundai logo",
    "url": "https://www.carlogos.org/car-logos/hyundai-logo.png"
  },
  {
    "alt": "Audi logo",
    "url": "https://www.carlogos.org/car-logos/audi-logo.png"
  },
  {
    "alt": "Jeep logo",
    "url": "https://www.carlogos.org/car-logos/jeep-logo.png"
  },
  {
    "alt": "Porsche logo",
    "url": "https://www.carlogos.org/car-logos/porsche-logo.png"
  },
  {
    "alt": "Dodge logo",
    "url": "https://www.carlogos.org/car-logos/dodge-logo.png"
  },
  {
    "alt": "Ferrari logo",
    "url": "https://www.carlogos.org/car-logos/ferrari-logo.png"
  },
  {
    "alt": "Jaguar logo",
    "url": "https://www.carlogos.org/car-logos/jaguar-logo.png"
  },
  {
    "alt": "Lamborghini logo",
    "url": "https://www.carlogos.org/car-logos/lamborghini-logo.png"
  },
  {
    "alt": "Maserati logo",
    "url": "https://www.carlogos.org/car-logos/maserati-logo.png"
  },
  {
    "alt": "Bentley logo",
    "url": "https://www.carlogos.org/car-logos/bentley-logo.png"
  },
  {
    "alt": "Chrysler logo",
    "url": "https://www.carlogos.org/car-logos/chrysler-logo.png"
  },
  {
    "alt": "Chevrolet Corvette logo",
    "url": "https://www.carlogos.org/car-logos/corvette-logo.png"
  },
  {
    "alt": "Cadillac logo",
    "url": "https://www.carlogos.org/car-logos/cadillac-logo.png"
  },
  {
    "alt": "Mazda logo",
    "url": "https://www.carlogos.org/car-logos/mazda-logo.png"
  },
  {
    "alt": "Ford Mustang logo",
    "url": "https://www.carlogos.org/car-logos/ford-mustang-logo.png"
  },
  {
    "alt": "Nissan logo",
    "url": "https://www.carlogos.org/car-logos/nissan-logo.png"
  },
  {
    "alt": "Alfa Romeo logo",
    "url": "https://www.carlogos.org/car-logos/alfa-romeo-logo.png"
  },
  {
    "alt": "Bugatti logo",
    "url": "https://www.carlogos.org/car-logos/bugatti-logo.png"
  },
  {
    "alt": "Buick logo",
    "url": "https://www.carlogos.org/car-logos/buick-logo.png"
  },
  {
    "alt": "Lexus logo",
    "url": "https://www.carlogos.org/car-logos/lexus-logo.png"
  },
  {
    "alt": "Rolls-Royce logo",
    "url": "https://www.carlogos.org/car-logos/rolls-royce-logo.png"
  },
  {
    "alt": "Acura logo",
    "url": "https://www.carlogos.org/car-logos/acura-logo.png"
  },
  {
    "alt": "Aston Martin logo",
    "url": "https://www.carlogos.org/car-logos/aston-martin-logo.png"
  },
  {
    "alt": "Chevrolet logo",
    "url": "https://www.carlogos.org/car-logos/chevrolet-logo.png"
  },
  {
    "alt": "Kia logo",
    "url": "https://www.carlogos.org/car-logos/kia-logo.png"
  },
  {
    "alt": "Mercedes-Benz logo",
    "url": "https://www.carlogos.org/car-logos/mercedes-benz-logo.png"
  },
  {
    "alt": "Volkswagen logo",
    "url": "https://www.carlogos.org/car-logos/volkswagen-logo.png"
  },
  {
    "alt": "Volvo logo",
    "url": "https://www.carlogos.org/car-logos/volvo-logo.png"
  },
  {
    "alt": "McLaren logo",
    "url": "https://www.carlogos.org/car-logos/mclaren-logo.png"
  },
  {
    "alt": "Mitsubishi logo",
    "url": "https://www.carlogos.org/car-logos/mitsubishi-logo.png"
  },
  {
    "alt": "GMC logo",
    "url": "https://www.carlogos.org/car-logos/gmc-logo.png"
  },
  {
    "alt": "Infiniti logo",
    "url": "https://www.carlogos.org/car-logos/infiniti-logo.png"
  },
  {
    "alt": "Lincoln logo",
    "url": "https://www.carlogos.org/car-logos/lincoln-logo.png"
  },
  {
    "alt": "Peugeot logo",
    "url": "https://www.carlogos.org/car-logos/peugeot-logo.png"
  },
  {
    "alt": "Pontiac logo",
    "url": "https://www.carlogos.org/car-logos/pontiac-logo.png"
  },
  {
    "alt": "Saab logo",
    "url": "https://www.carlogos.org/car-logos/saab-logo.png"
  },
  {
    "alt": "Genesis logo",
    "url": "https://www.carlogos.org/car-logos/genesis-logo.png"
  },
  {
    "alt": "Suzuki logo",
    "url": "https://www.carlogos.org/car-logos/suzuki-logo.png"
  },
  {
    "alt": "Citroën logo",
    "url": "https://www.carlogos.org/car-logos/citroen-logo.png"
  },
  {
    "alt": "Fiat logo",
    "url": "https://www.carlogos.org/car-logos/fiat-logo.png"
  },
  {
    "alt": "Lotus logo",
    "url": "https://www.carlogos.org/car-logos/lotus-logo.png"
  },
  {
    "alt": "Mini logo",
    "url": "https://www.carlogos.org/car-logos/mini-logo.png"
  },
  {
    "alt": "Peterbilt logo",
    "url": "https://www.carlogos.org/car-logos/peterbilt-logo.png"
  },
  {
    "alt": "Saturn logo",
    "url": "https://www.carlogos.org/car-logos/saturn-logo.png"
  },
  {
    "alt": "BMW M logo",
    "url": "https://www.carlogos.org/car-logos/bmw-m-logo.png"
  },
  {
    "alt": "General Motors logo",
    "url": "https://www.carlogos.org/car-logos/general-motors-logo.png"
  },
  {
    "alt": "Kenworth logo",
    "url": "https://www.carlogos.org/car-logos/kenworth-logo.png"
  },
  {
    "alt": "KTM logo",
    "url": "https://www.carlogos.org/car-logos/ktm-logo.png"
  }
]